Metadata-Version: 1.1
Name: pandoc-lettrine
Version: 0.1.0
Summary: A pandoc filter for lettrine (drop caps) styling.
